[{"id":0,"name":"placeholder","score":1000,"time":1726623162575},{"id":1,"name":"placeholder","score":1900,"time":1726623449591},{"id":0,"name":"placeholder","score":400,"time":1726625069574},{"id":1,"name":"placeholder","score":100,"time":1726625135244},{"id":2,"name":"placeholder","score":100,"time":1726625135246},{"id":3,"name":"placeholder","score":100,"time":1726625135749},{"id":4,"name":"placeholder","score":100,"time":1726625135753},{"id":5,"name":"placeholder","score":100,"time":1726625139989},{"id":6,"name":"placeholder1","score":100,"time":1726625162873},{"name":"placeholder1","score":100,"time":1726625564629},{"name":"placeholder1","score":100,"time":1726625628031}]